intrepid_python_sdk/__init__.py
intrepid_python_sdk/cache_manager.py
intrepid_python_sdk/config.py
intrepid_python_sdk/config_manager.py
intrepid_python_sdk/constants.py
intrepid_python_sdk/decorators.py
intrepid_python_sdk/errors.py
intrepid_python_sdk/log_manager.py
intrepid_python_sdk/message.py
intrepid_python_sdk/node.py
intrepid_python_sdk/qos.py
intrepid_python_sdk/simulator/__init__.py
intrepid_python_sdk/simulator/entity.py
intrepid_python_sdk/simulator/sim_client.py
intrepid_python_sdk/simulator/simulator.py
intrepid_python_sdk/simulator/vehicle.py
intrepid_python_sdk/status.py
intrepid_python_sdk/utils.py
intrepid_python_sdk/ws_helper.py
intrepid_python_sdk-0.1.12.dist-info/LICENSE
intrepid_python_sdk-0.1.12.dist-info/METADATA
intrepid_python_sdk-0.1.12.dist-info/WHEEL
intrepid_python_sdk-0.1.12.dist-info/RECORD
